aicostmanager/__init__.py
aicostmanager/config_manager.py
aicostmanager/costs.py
aicostmanager/ini_manager.py
aicostmanager/logger.py
aicostmanager/queue_monitor.py
aicostmanager/tracker.py
aicostmanager/triggered_limits_cache.py
aicostmanager/type_validator.py
aicostmanager/usage_utils.py
aicostmanager/wrappers.py
aicostmanager/client/__init__.py
aicostmanager/client/async_client.py
aicostmanager/client/base.py
aicostmanager/client/exceptions.py
aicostmanager/client/sync_client.py
aicostmanager/delivery/__init__.py
aicostmanager/delivery/base.py
aicostmanager/delivery/factory.py
aicostmanager/delivery/immediate.py
aicostmanager/delivery/persistent.py
aicostmanager/delivery/persistent_queue_manager.py
aicostmanager/limits/__init__.py
aicostmanager/limits/base.py
aicostmanager/limits/triggered.py
aicostmanager/limits/usage.py
aicostmanager/models/__init__.py
aicostmanager/models/analytics.py
aicostmanager/models/common.py
aicostmanager/models/config.py
aicostmanager/models/costs.py
aicostmanager/models/custom_services.py
aicostmanager/models/customers.py
aicostmanager/models/limits.py
aicostmanager/models/reports.py
aicostmanager/models/schedules.py
aicostmanager/models/services.py
aicostmanager/models/usage.py
aicostmanager/models/webhooks.py
aicostmanager/utils/ini_utils.py
examples/heygen_sync.py
aicostmanager-0.1.41.dist-info/METADATA
aicostmanager-0.1.41.dist-info/WHEEL
aicostmanager-0.1.41.dist-info/entry_points.txt
aicostmanager-0.1.41.dist-info/top_level.txt
aicostmanager-0.1.41.dist-info/RECORD
