Metadata-Version: 2.4
Name: aicostmanager
Version: 0.1.41
Summary: Python SDK for the AICostManager API
Author-email: AICostManager <support@aicostmanager.com>
Project-URL: Homepage, https://aicostmanager.com
Project-URL: Source, https://github.com/aicostmanager/aicostmanager-python
Requires-Python: >=3.9
Requires-Dist: requests
Requires-Dist: pydantic
Requires-Dist: httpx
Requires-Dist: PyJWT
Requires-Dist: tenacity
Requires-Dist: cryptography
Provides-Extra: dev
Requires-Dist: build; extra == "dev"
Requires-Dist: twine; extra == "dev"
Requires-Dist: bump-my-version; extra == "dev"
